Workbook

Sheet Sammlung Start
A1: Sammlung – Gesamtübersicht
A2: Postkarten und Münzen getrennt bewertet, gemeinsam im Blick
A4: Artikel gesamt | C4: Aktueller Gesamt-VK | E4: Marktwert gesamt | G4: Differenz zum Markt | I4: Preisabweichungen | L4: Münzen prüfen
A5: =COUNTA(Postkarten!A2:'Postkarten'!A616)+COUNTA(Münzen!A5:A13) -> 623 | C5: =SUM(Postkarten!N2:'Postkarten'!N622)+SUM(Münzen!N5:N13) -> 5335.9 | E5: =SUM(Preisvergleich[Ermittelt VK])+SUM(MuenzenPreisvergleich[Ermittelt VK]) -> 3576.4 | G5: =E5-C5 -> -1759.5 | I5: =COUNTIF(Preisvergleich[Differenz VK],"<>0")+COUNTIF(MuenzenPreisvergleich[Differenz VK],"<>0") -> 68 | L5: =COUNTIF(MuenzenPreisvergleich[Bewertung],"Identifikation prüfen") -> 5
A9: Sammlungsbereich | B9: Artikel | C9: Aktueller VK | D9: Marktwert | E9: Differenz | G9: Bereich | H9: Erhöhen | I9: Senken | J9: Unverändert | K9: Identifikation prüfen
A10: Postkarten | B10: =COUNTA(Postkarten!A2:A410) -> 408 | C10: =SUM(Postkarten!N2:N410) -> 3303.4 | D10: =SUM(Preisvergleich[Ermittelt VK]) -> 3224.4 | E10: =D10-C10 -> -79 | G10: Postkarten | H10: =COUNTIF(Preisvergleich[Bewertung],"Erhöhen") -> 12 | I10: =COUNTIF(Preisvergleich[Bewertung],"Senken") -> 52 | J10: =COUNTIF(Preisvergleich[Bewertung],"Unverändert") -> 344 | K10: 0
A11: Münzen | B11: =COUNTA(Münzen!A5:A13) -> 9 | C11: =SUM(Münzen!N5:N13) -> 340 | D11: =SUM(MuenzenPreisvergleich[Ermittelt VK]) -> 352 | E11: =D11-C11 -> 12 | G11: Münzen | H11: =COUNTIF(MuenzenPreisvergleich[Bewertung],"Erhöhen") -> 2 | I11: =COUNTIF(MuenzenPreisvergleich[Bewertung],"Senken") -> 1 | J11: =COUNTIF(MuenzenPreisvergleich[Bewertung],"Unverändert") -> 1 | K11: =COUNTIF(MuenzenPreisvergleich[Bewertung],"Identifikation prüfen") -> 5
A14: Empfohlene Reihenfolge
A15: 1 | B15: Postkarten Dashboard | C15: Verkaufssteuerung, Orte, Preisbereiche und Top-Angebote
A16: 2 | B16: Postkarten Vergleich | C16: Marktwerte und Preisabweichungen aller Postkarten
A17: 3 | B17: Münzen | C17: Bestand, Erhaltungsgrade und eigene Preisansätze
A18: 4 | B18: Münzen Vergleich | C18: Marktwerte und Identifikationshinweise der Münzen
A21: Hinweis zum Münzfoto: Die neun Münzen sind sichtbar, aber Jahrgänge, Nominale und Münzzeichen sind nicht bei allen Stücken sicher lesbar. Die mit „Identifikation prüfen“ markierten Bewertungen bleiben vorläufig, bis Vorder- und Rückseite jeder Münze einzeln fotografiert wurden.

Sheet Postkarten Dashboard
A1: Webshop-Start: Verkaufsübersicht
A2: Bestand, Preispositionierung und Datenqualität für einen strukturierten Verkaufsstart
A4: Karten | C4: Aktueller VK | E4: Ø VK / Karte | G4: Marktvergleich | I4: Preis anpassen | K4: Artikel-Duplikate
A5: =COUNTA(Postkarten!$A$2:$A$695) -> 635 | C5: =SUM(Postkarten!$N$2:$N$695) -> 5101.9 | E5: =IFERROR(C5/A5,0) -> 8.0344882 | G5: =IFERROR(COUNTIF(Preisvergleich[Artikelnummer],"AK-*")/A5,0) -> 0.64251969 | I5: =COUNTIFS(Preisvergleich[Artikelnummer],"AK-*",Preisvergleich[Differenz VK],"<>0") -> 64 | K5: {=COUNTA(_xlfn._xlws.FILTER(Postkarten!$A$2:$A$410,Postkarten!$A$2:$A$410<>""))-ROWS(_xlfn.UNIQUE(_xlfn._xlws.FILTER(Postkarten!$A$2:$A$410,Postkarten!$A$2:$A$410<>"")))} -> 0
A8: Top-Orte | B8: Karten | C8: VK-Summe | E8: Preissegment | F8: Karten | G8: VK-Summe | I8: Datenqualität | J8: Offen | K8: Priorität
A9: München | B9: =COUNTIF(Postkarten!$D$2:$D$410,A9&"*") -> 54 | C9: =SUMIF(Postkarten!$D$2:$D$410,A9&"*",Postkarten!$N$2:$N$410) -> 492 | E9: Premium (≥ 12 €) | F9: =COUNTIF(Postkarten!$N$2:$N$410,">=12") -> 46 | G9: =SUMIF(Postkarten!$N$2:$N$410,">=12",Postkarten!$N$2:$N$410) -> 670.4 | I9: Ohne Marktvergleich | J9: =A5-ROWS(Preisvergleich[Artikelnummer]) -> 227 | K9: Hoch
A10: Regensburg | B10: =COUNTIF(Postkarten!$D$2:$D$410,A10&"*") -> 42 | C10: =SUMIF(Postkarten!$D$2:$D$410,A10&"*",Postkarten!$N$2:$N$410) -> 333.5 | E10: Kernsortiment (8–11,99 €) | F10: =COUNTIFS(Postkarten!$N$2:$N$410,">=8",Postkarten!$N$2:$N$410,"<12") -> 152 | G10: =SUMIFS(Postkarten!$N$2:$N$410,Postkarten!$N$2:$N$410,">=8",Postkarten!$N$2:$N$410,"<12") -> 1362 | I10: Doppelte Artikelnummern | J10: =K5 -> 0 | K10: Hoch
A11: Nürnberg | B11: =COUNTIF(Postkarten!$D$2:$D$410,A11&"*") -> 24 | C11: =SUMIF(Postkarten!$D$2:$D$410,A11&"*",Postkarten!$N$2:$N$410) -> 198.5 | E11: Standard (5–7,99 €) | F11: =COUNTIFS(Postkarten!$N$2:$N$410,">=5",Postkarten!$N$2:$N$410,"<8") -> 201 | G11: =SUMIFS(Postkarten!$N$2:$N$410,Postkarten!$N$2:$N$410,">=5",Postkarten!$N$2:$N$410,"<8") -> 1234 | I11: Verlag unbekannt | J11: =COUNTIF(Postkarten!$C$2:$C$410,"*Unbekannt*") -> 73 | K11: Mittel
A12: Parsberg | B12: =COUNTIF(Postkarten!$D$2:$D$410,A12&"*") -> 22 | C12: =SUMIF(Postkarten!$D$2:$D$410,A12&"*",Postkarten!$N$2:$N$410) -> 218.4 | E12: Bündel (< 5 €) | F12: =COUNTIF(Postkarten!$N$2:$N$410,"<5") -> 10 | G12: =SUMIF(Postkarten!$N$2:$N$410,"<5",Postkarten!$N$2:$N$410) -> 37 | I12: Jahr unklar | J12: =COUNTIF(Postkarten!$I$2:$I$410,"*Unbekannt*")+COUNTIF(Postkarten!$I$2:$I$410,"Keiner") -> 74 | K12: Mittel
A13: Lupburg | B13: =COUNTIF(Postkarten!$D$2:$D$410,A13&"*") -> 13 | C13: =SUMIF(Postkarten!$D$2:$D$410,A13&"*",Postkarten!$N$2:$N$410) -> 139 | I13: Stempel unklar | J13: =COUNTIF(Postkarten!$J$2:$J$410,"*Unbekannt*")+COUNTIF(Postkarten!$J$2:$J$410,"Keiner") -> 93 | K13: Niedrig
A14: Donaustauf | B14: =COUNTIF(Postkarten!$D$2:$D$410,A14&"*") -> 8 | C14: =SUMIF(Postkarten!$D$2:$D$410,A14&"*",Postkarten!$N$2:$N$410) -> 75 | I14: Empfänger/Absender unklar | J14: =COUNTIF(Postkarten!$K$2:$K$410,"*Unbekannt*")+COUNTIF(Postkarten!$K$2:$K$410,"Keine") -> 112 | K14: Niedrig
A15: Herrenchiemsee | B15: =COUNTIF(Postkarten!$D$2:$D$410,A15&"*") -> 7 | C15: =SUMIF(Postkarten!$D$2:$D$410,A15&"*",Postkarten!$N$2:$N$410) -> 46
A16: Oberammergau | B16: =COUNTIF(Postkarten!$D$2:$D$410,A16&"*") -> 7 | C16: =SUMIF(Postkarten!$D$2:$D$410,A16&"*",Postkarten!$N$2:$N$410) -> 64
A17: Rothenburg ob der Tauber | B17: =COUNTIF(Postkarten!$D$2:$D$410,A17&"*") -> 7 | C17: =SUMIF(Postkarten!$D$2:$D$410,A17&"*",Postkarten!$N$2:$N$410) -> 48
A18: Passau | B18: =COUNTIF(Postkarten!$D$2:$D$410,A18&"*") -> 5 | C18: =SUMIF(Postkarten!$D$2:$D$410,A18&"*",Postkarten!$N$2:$N$410) -> 37
A21: Verkaufspriorität – höchste aktuelle Einzelwerte | J21: Start-Checkliste
A22: Rang | B22: Artikelnummer | C22: Titel | D22: Ort | E22: VK | F22: Markt-VK | G22: Differenz | H22: Empfehlung | J22: Nr. | K22: Aufgabe | L22: Umfang | M22: Status | N22: Nutzen
A23: {=_xlfn.LET(_xlpm.ids,_xlfn._xlws.FILTER(Postkarten!$A$2:$A$410,Postkarten!$A$2:$A$410<>""),_xlpm.ttl,_xlfn._xlws.FILTER(Postkarten!$B$2:$B$410,Postkarten!$A$2:$A$410<>""),_xlpm.ort,_xlfn._xlws.FILTER(Postkarten!$D$2:$D$410,Postkarten!$A$2:$A$410<>""),_xlpm.vk,_xlfn._xlws.FILTER(Postkarten!$N$2:$N$410,Postkarten!$A$2:$A$410<>""),_xlpm.d,_xlfn.HSTACK(_xlpm.ids,_xlpm.ttl,_xlpm.ort,_xlpm.vk),_xlpm.z,_xlfn.TAKE(_xlfn.SORTBY(_xlpm.d,_xlpm.vk,-1),12),_xlpm.mv,_xlfn.XLOOKUP(_xlfn.CHOOSECOLS(_xlpm.z,1),Preisvergleich[Artikelnummer],Preisvergleich[Ermittelt VK],0),_xlpm.df,_xlpm.mv-_xlfn.CHOOSECOLS(_xlpm.z,4),_xlfn.HSTACK(_xlfn.SEQUENCE(12),_xlpm.z,_xlpm.mv,_xlpm.df,IF(_xlpm.df>0,"Erhöhen",IF(_xlpm.df<0,"Senken","Unverändert"))))} -> 1 | B23: AK-2026-0331 | C23: Gilching, Villenkolonie | D23: Gilching / Oberbayern / Bayern | E23: 28 | F23: 28 | G23: 0 | H23: Unverändert | J23: 1 | K23: Fehlende Marktvergleiche ergänzen | L23: =A5-ROWS(Preisvergleich[Artikelnummer]) -> 227 | M23: =IF(L23=0,"Bereit","Offen") -> Offen | N23: Preisrisiko reduzieren
A24: 2 | B24: AK-2026-0026 | C24: Dürnsricht – Blick auf Dürnsricht mit Bäckerei & Kolonialwarengeschäft Bartmann | D24: Dürnsricht | E24: 25 | F24: 25 | G24: 0 | H24: Unverändert | J24: 2 | K24: Doppelte Artikelnummern bereinigen | L24: =K5 -> 0 | M24: =IF(L24=0,"Bereit","Offen") -> Bereit | N24: Bestellungen eindeutig zuordnen
A25: 3 | B25: AK-2026-0268 | C25: München - Klapp-Werbebriefkarte Drei Masken Verlag | D25: München / Oberbayern | E25: 22 | F25: 22 | G25: 0 | H25: Unverändert | J25: 3 | K25: Premium-Karten einzeln fotografieren | L25: =F9 -> 46 | M25: Offen | N25: Höherer Erlös je Listing
A26: 4 | B26: AK-2026-0370 | C26: Schloss Herrenchiemsee – Salle de l'oeil de boeuf (Ochsenaugensaal) | D26: Chiemsee / Herrenchiemsee / Oberbayern / Bayern | E26: 22 | F26: 22 | G26: 0 | H26: Unverändert | J26: 4 | K26: Standardkarten zu Themen-Bundles bündeln | L26: =F12 -> 10 | M26: Offen | N26: Aufwand und Versand senken
A27: 5 | B27: AK-2026-0344 | C27: Walhalla a. Donau bei Regensburg (Erbaut 1830–1842 durch König Ludwig I., Entwurf von Leo von Klenze) | D27: Donaustauf / Regensburg / Oberpfalz / Bayern | E27: 20 | F27: 20 | G27: 0 | H27: Unverändert | J27: 5 | K27: Verlagsangaben nachpflegen | L27: =J11 -> 73 | M27: Offen | N27: Suche und SEO verbessern
A28: 6 | B28: AK-2026-0345 | C28: Gaststätte „Tiroler Höhe“ Nürnberg-S. am Hasenbuck | D28: Nürnberg / Mittelfranken / Bayern[cite: 14] | E28: 20 | F28: 6 | G28: -14 | H28: Senken | J28: 6 | K28: Datierung nachpflegen | L28: =J12 -> 74 | M28: Offen | N28: Sammlerrelevanz erhöhen
A29: 7 | B29: AK-2026-0133 | C29: XXIII. Bundestag des D. R. B. Nürnberg (Kaiserburg) | D29: Nürnberg | E29: 19 | F29: 19 | G29: 0 | H29: Unverändert | J29: 7 | K29: Listing-Mindeststandard erfüllt | L29: =A5 -> 635 | M29: Bereit | N29: Titel, Zustand, Preis, Status vorhanden
A30: 8 | B30: AK-2026-0084 | C30: Prinz Regent Luitpold von Bayern – Jubiläums-Postkarte 1821–1911 | D30: München / Bayern | E30: 18 | F30: 12 | G30: -6 | H30: Senken
A31: 9 | B31: AK-2026-0085 | C31: Prinz Regent Luitpold von Bayern – Jubiläums-Postkarte mit Mädchen (1911) | D31: München / Bayern | E31: 18 | F31: 12 | G31: -6 | H31: Senken
A32: 10 | B32: AK-2026-0158 | C32: Granit-Steinbruch Zeinried! | D32: Zeinried / Oberpfalz | E32: 18 | F32: 18 | G32: 0 | H32: Unverändert
A33: 11 | B33: AK-2026-0017 | C33: Regensburg – Moltkeplatz im Schnee (Nachtschneekarte mit Dom) | D33: Regensburg | E33: 15 | F33: 15 | G33: 0 | H33: Unverändert
A34: 12 | B34: AK-2026-0111 | C34: Blick auf München vom Maximilianeum aus | D34: München | E34: 15 | F34: 15 | G34: 0 | H34: Unverändert
A37: Größte Preis-Chancen laut Vergleich | J37: Preis-Senkungen mit höchster Dringlichkeit
A38: Artikelnummer | B38: Titel | C38: Aktuell VK | D38: Markt-VK | E38: Potenzial | F38: Ort | G38: Quellzeile | H38: Aktion | J38: Artikelnummer | K38: Titel | L38: Aktuell | M38: Markt | N38: Differenz
A39: {=IFERROR(_xlfn.LET(_xlpm.d,_xlfn._xlws.FILTER(_xlfn.HSTACK(Preisvergleich[Artikelnummer],Preisvergleich[Titel],Preisvergleich[Aktuell VK],Preisvergleich[Ermittelt VK],Preisvergleich[Differenz VK],_xlfn.XLOOKUP(Preisvergleich[Artikelnummer],Postkarten!A2:A410,Postkarten!D2:D410,""),Preisvergleich[Quellzeile]),(Preisvergleich[Differenz VK]>0)*(LEFT(Preisvergleich[Artikelnummer],3)="AK-")),_xlpm.z,_xlfn.TAKE(_xlfn.SORTBY(_xlpm.d,_xlfn.CHOOSECOLS(_xlpm.d,5),-1),10),_xlfn.HSTACK(_xlpm.z,IF(_xlfn.CHOOSECOLS(_xlpm.z,5)>0,"Preis prüfen/erhöhen",""))),"Keine Erhöhungen offen")} -> AK-2026-0396 | B39: Gruß aus Ensdorf bei Amberg Opf. | C39: 7 | D39: 14 | E39: 7 | F39: Ensdorf / Oberpfalz / Bayern | G39: 398 | H39: Preis prüfen/erhöhen | J39: {=_xlfn.LET(_xlpm.d,_xlfn._xlws.FILTER(_xlfn.HSTACK(Preisvergleich[Artikelnummer],Preisvergleich[Titel],Preisvergleich[Aktuell VK],Preisvergleich[Ermittelt VK],Preisvergleich[Differenz VK]),(Preisvergleich[Differenz VK]<0)*(LEFT(Preisvergleich[Artikelnummer],3)="AK-")),_xlfn.TAKE(_xlfn.SORTBY(_xlpm.d,_xlfn.CHOOSECOLS(_xlpm.d,5),1),10))} -> AK-2026-0345 | K39: Gaststätte „Tiroler Höhe“ Nürnberg-S. am Hasenbuck | L39: 20 | M39: 6 | N39: -14
A40: AK-2026-0397 | B40: Ansbach – Krankenhaus | C40: 6 | D40: 13 | E40: 7 | F40: Ansbach / Mittelfranken / Bayern | G40: 399 | H40: Preis prüfen/erhöhen | J40: AK-2026-0084 | K40: Prinz Regent Luitpold von Bayern – Jubiläums-Postkarte 1821–1911 | L40: 18 | M40: 12 | N40: -6
A41: AK-2026-0384 | B41: Roth a/ See | C41: 6 | D41: 9 | E41: 3 | F41: Roth an der Saale / Unterfranken / Bayern | G41: 386 | H41: Preis prüfen/erhöhen | J41: AK-2026-0085 | K41: Prinz Regent Luitpold von Bayern – Jubiläums-Postkarte mit Mädchen (1911) | L41: 18 | M41: 12 | N41: -6
A42: AK-2026-0400 | B42: Schloß Parsberg / Bayrische Oberpfalz | C42: 7 | D42: 10 | E42: 3 | F42: Parsberg / Oberpfalz / Bayern | G42: 402 | H42: Preis prüfen/erhöhen | J42: AK-2026-0343 | K42: München - Ehrentempel am Königlichen Platz | L42: 10 | M42: 6 | N42: -4
A43: AK-2026-0382 | B43: Zenting, bayr. Wald | C43: 4 | D43: 6 | E43: 2 | F43: Zenting / Niederbayern / Bayern | G43: 384 | H43: Preis prüfen/erhöhen | J43: AK-2026-0156 | K43: Gruss vom Oberammergauer Passionsspiel (Bühnenansicht) | L43: 12 | M43: 9 | N43: -3
A44: AK-2026-0383 | B44: Zenting, bayr. Wald | C44: 4 | D44: 6 | E44: 2 | F44: Zenting / Niederbayern / Bayern | G44: 385 | H44: Preis prüfen/erhöhen | J44: AK-2026-0310 | K44: Gruß aus Seubersdorf (Mehrfach-Luftbildkarte) | L44: 12 | M44: 9 | N44: -3
A45: AK-2026-0236 | B45: Schwarzenkopfhütte über Neuhaus b. Schliersee | C45: 6 | D45: 8 | E45: 2 | F45: Schliersee / Oberbayern / Bayern | G45: 237 | H45: Preis prüfen/erhöhen | J45: AK-2026-0311 | K45: Feldkirchen b. Westerham gegen Wendelstein (1884 m) | L45: 9 | M45: 6 | N45: -3
A46: AK-2026-0381 | B46: Feste Koburg aus einem Flugzeug gesehen | C46: 5 | D46: 6 | E46: 1 | F46: Coburg / Oberfranken / Bayern | G46: 383 | H46: Preis prüfen/erhöhen | J46: AK-2026-0312 | K46: Luftbild Sulzbürg / Opf. | L46: 11 | M46: 8 | N46: -3
A47: AK-2026-0390 | B47: Regensburg – Blick auf die Stadt von den Winserer Höhen | C47: 6 | D47: 7 | E47: 1 | F47: Regensburg / Oberpfalz / Bayern | G47: 392 | H47: Preis prüfen/erhöhen | J47: AK-2026-0314 | K47: Seubersdorf Opf. (Mehrfach-Luftbildkarte mit Bäckerei Anton Liedl) | L47: 15 | M47: 12 | N47: -3
A48: AK-2026-0391 | B48: München – Total mit Frauenkirche | C48: 7 | D48: 8 | E48: 1 | F48: München / Oberbayern / Bayern | G48: 393 | H48: Preis prüfen/erhöhen | J48: AK-2026-0315 | K48: Bodensee - Panorama-Ansichtskarte mit Wappen | L48: 12 | M48: 9 | N48: -3

Sheet Postkarten
A1: Artikelnummer | B1: Titel | C1: Verlag | D1: Ort / Region | E1: Kategorie / Motiv | F1: Erhaltungszustand | G1: Zustand Details | H1: Gelaufen (J/N) | I1: Baujahr / Postamt | J1: Stempel Info | K1: Empfänger / Absender | L1: Wert Min (€) | M1: Wert Max (€) | N1: Verkaufspreis (€) | O1: Status | P1: Besondere Merkmale | Q1: Bekannte Mängel
A2: AK-2026-0001 | B2: München – Karlsplatz (Stachus) mit Steinbogen und Stadtwappen | C2: Historischer Kunstverlag | D2: München | E2: Topografie / Stadtansicht | F2: Gut (Z2) | G2: Schöne Lithografie mit Zierrahmen, gelaufen | H2: Ja | I2: ca. 1905 | J2: München Postamt | K2: Sammlungsbestand | L2: 4 | M2: 8 | N2: =MAX(L2,M2) -> 8 | O2: Im Bestand | P2: Lithografie, Wappen
A3: AK-2026-0002 | B3: Straubing – Ludwigsplatz (Blick vom unteren Tor) | C3: Lokaler Verlag Straubing | D3: Straubing | E3: Topografie / Straßenbild | F3: Gut (Z2) | G3: Vorderseitig beschrieben, sauberer Erhalt | H3: Ja | I3: ca. 1908 | J3: Straubing | K3: Sammlungsbestand | L3: 3 | M3: 6 | N3: =MAX(L3,M3) -> 6 | O3: Im Bestand | P3: Historischer Straßenzug
A4: AK-2026-0003 | B4: Nürnberg – Schöner Brunnen mit Marktgeschehen | C4: Ottmar Zieher | D4: Nürnberg | E4: Topografie / Sehenswürdigkeit | F4: Altersentsprechend (Z2-3) | G4: Vorderseite stark beschrieben, optischer Zustand etwas eingeschränkt | H4: Ja | I4: ca. 1906 | J4: Nürnberg | K4: Sammlungsbestand | L4: 2.5 | M4: 5 | N4: =MAX(L4,M4) -> 5 | O4: Im Bestand | P4: Marktgeschehen, beschriebene Vorderseite
A5: AK-2026-0004 | B5: Beratzhausen – Gesamtansicht (gelaufen über Holnstein nach Lupburg) | C5: Lokaler Verlag | D5: Beratzhausen / Holnstein | E5: Topografie / Oberpfalz | F5: Sehr gut (Z1-2) | G5: Sauber gestempelt, schöne Handschrift | H5: Ja | I5: 1909 | J5: Holnstein / Lupburg | K5: An Josef Pauerer | L5: 4 | M5: 7 | N5: =MAX(L5,M5) -> 7 | O5: Im Bestand | P5: Heimatkarte Oberpfalz, Stempel Holnstein
A6: AK-2026-0005 | B6: München – Künstler-Jubiläumskarte 1821–1911 (W. Diez, Oscar Consée) | C6: Oscar Consée, München 5 | D6: München | E6: Künstlerkarte / Jubiläum | F6: Sehr gut (Z1) | G6: Ungelaufen, brillante Farben | H6: Nein | I6: 1910 / 1911 | J6: Ungestempelt | K6: Unbeschrieben | L6: 6 | M6: 12 | N6: =MAX(L6,M6) -> 12 | O6: Im Bestand | P6: Signiert W. Diez, Prinzregent Luitpold Jubiläum
A7: AK-2026-0006 | B7: München – Künstler-Jubiläumskarte 1821–1911 (gelaufen nach Beratzhausen 1911) | C7: Oscar Consée, München 5 | D7: München / Beratzhausen | E7: Künstlerkarte / Jubiläum | F7: Gut (Z2) | G7: Gelaufen mit Marke und Stempel Lupburg 1911 | H7: Ja | I7: 1911 | J7: Lupburg, 10.03.1911 | K7: Josef Pauerer / Josef Vogl Geschwister | L7: 8 | M7: 14 | N7: =MAX(L7,M7) -> 14 | O7: Im Bestand | P7: Sütterlin-Text, Prinzregent Luitpold
A8: AK-2026-0007 | B8: München – Künstler-Jubiläumskarte 1911 mit Kindern (gelaufen nach Beratzhausen) | C8: Oscar Consée, München 5 | D8: München / Beratzhausen | E8: Künstlerkarte / Jubiläum | F8: Befriedigend bis Gut (Z2-3) | G8: Starke Flecken/Verschmutzungen am Unterrand | H8: Ja | I8: 1911 | J8: Lupburg, 10.03.1911 | K8: Josef Pauerer / Vater, Mutti & Geschwister | L8: 3 | M8: 6 | N8: =MAX(L8,M8) -> 6 | O8: Im Bestand | P8: Kindermotiv, Randverschmutzungen
A9: AK-2026-0008 | B9: München – Künstler-Jubiläumskarte 1911 mit Kindern (ungelaufen, Randspuren) | C9: Oscar Consée, München 5 | D9: München | E9: Künstlerkarte / Jubiläum | F9: Befriedigend bis Gut (Z2-3) | G9: Vorderseitig leichte Klebe- und Schmutzspuren unten, ungelaufen | H9: Nein | I9: ca. 1911 | J9: Ungestempelt | K9: Unbeschrieben | L9: 3 | M9: 6 | N9: =MAX(L9,M9) -> 6 | O9: Im Bestand | P9: Kindermotiv, ungelaufene Variante
A10: AK-2026-0009 | B10: München – Künstler-Jubiläumskarte 1911 mit Kindern (sauberer Zustand, ungelaufen) | C10: Oscar Consée, München 5 | D10: München | E10: Künstlerkarte / Jubiläum | F10: Sehr gut (Z1-2) | G10: Vorderseite sauber, Kanten gut erhalten, ungelaufen | H10: Nein | I10: ca. 1911 | J10: Ungestempelt | K10: Unbeschrieben | L10: 5 | M10: 9 | N10: =MAX(L10,M10) -> 9 | O10: Im Bestand | P10: Kindermotiv, sehr guter Zustand
A11: AK-2026-0010 | B11: Nürnberg – Prinzregenten-Denkmal mit Edelweiß-Prägung | C11: Paul Seyfert, Dresden (No. 904) | D11: Nürnberg | E11: Denkmäler / Prägekarte | F11: Sehr gut (Z1-2) | G11: Vorderseite kräftige Prägung, leichte Eckenbestoßung unten; gelaufen mit 5-Pfennig Bayern-Marke | H11: Ja | I11: 1901 | J11: Nürnberg / Schleiz, 03.05.1901 | K11: Otto Rahtel, b. Schleiz (Reuß) | L11: 6 | M11: 12 | N11: =MAX(L11,M11) -> 12 | O11: Im Bestand | P11: Prägung / Relief, Edelweiß, Sütterlin / Handschrift
A12: AK-2026-0011 | B12: Regensburg – Emmeranerthor mit Seitenflügel des Fürstlichen Taxis Palais | C12: Jacob Frankel, Regensburg (No. 565) | D12: Regensburg | E12: Topografie / Lithografie | F12: Sehr gut (Z1-2) | G12: Vorderseitig mit Wappen und Relief, gelaufen mit 5-Pfennig Bayern-Marke | H12: Ja | I12: 1901 | J12: Regensburg / Wiesenfelden, 13.12.1901 | K12: Hochwürden Herrn Pfarrer Anton Windhager, Wiesenfelden b. Wörth a.d. Donau | L12: 6 | M12: 12 | N12: =MAX(L12,M12) -> 12 | O12: Im Bestand | P12: Lithografie, Wappen, Relief, Fürst Thurn und Taxis
A13: AK-2026-0012 | B13: Passau – Panorama-Gesamtansicht vom Fluss aus | C13: A. Hermann, Passau | D13: Passau | E13: Topografie / Lithografie | F13: Gut (Z2) | G13: Vorderseitig mit handschriftlichem Text, gelaufen mit 5-Pfennig Bayern-Marke | H13: Ja | I13: 1903 | J13: Passau / Wiesenfelden, 27.08.1903 | K13: Hochwürden Herrn Pfarrer Anton Windhager, Wiesenfelden b. Wörth a.d. Donau | L13: 5 | M13: 10 | N13: =MAX(L13,M13) -> 10 | O13: Im Bestand | P13: Kolorierte Lithografie, Flussansicht, Sütterlin / Handschrift
A14: AK-2026-0013 | B14: München – Karlstor mit bayerischem Wappen und Löwen | C14: Historischer Kunstverlag / Litho | D14: München | E14: Topografie / Lithografie | F14: Sehr gut (Z1-2) | G14: Prächtige Wappen-Lithografie mit Sütterlin-Text, gelaufen mit 5-Pfennig Bayern-Marke | H14: Ja | I14: 1901 | J14: München / Straubing / Wiesenfelden, 18.08.1901 | K14: Hochwürden Herrn Pfarrer Anton Windhager, Wiesenfelden b. Wörth a.d. Donau | L14: 6 | M14: 12 | N14: =MAX(L14,M14) -> 12 | O14: Im Bestand | P14: Lithografie, Bayerisches Wappen, Löwen, Karlstor
A15: AK-2026-0014 | B15: Regensburg – Gruss aus Regensburg (Dom, Bischof Ignatius, Altar) | C15: Verlag von Jakob Frankel, Regensburg (No. 100) | D15: Regensburg | E15: Topografie / Mehrbild-Lithografie | F15: Gut (Z2) | G15: Mehrbild-Lithografie mit Porträt Bischof Ignatius, gelaufen mit 5-Pfennig Bayern-Marke | H15: Ja | I15: 1900 | J15: Regensburg / Straubing / Wiesenfelden, 09.06.1900 | K15: H. Hochwürden Herrn Pfarrer Anton Windhager, Wiesenfelden b. Wörth a.d. Donau | L15: 5 | M15: 10 | N15: =MAX(L15,M15) -> 10 | O15: Im Bestand | P15: Lithografie, Bischof Ignatius, Dom Regensburg, Mehrbild
A16: AK-2026-0015 | B16: München – Gruss vom Hofbräuhaus (Junge mit Bierkrug und Dackel) | C16: Ottmar Zieher, München | D16: München | E16: Künstlerkarte / Humor | F16: Sehr gut (Z1-2) | G16: Farbige Litho mit Junge in Tracht und Dackel, gelaufen mit 5-Pfennig Bayern-Marke | H16: Ja | I16: 1902 | J16: Straubing / Wiesenfelden, 11.03.1902 | K16: Hochwürden Herrn Pfarrer Anton Windhager, Wiesenfelden b. Wörth a.d. Donau | L16: 6 | M16: 12 | N16: =MAX(L16,M16) -> 12 | O16: Im Bestand | P16: Ottmar Zieher Verlag, Hofbräuhaus, Dackel, Tracht
A17: AK-2026-0016 | B17: Regensburg – Gruss aus Regensburg (Walhalla, Brücke, Neupfarrkirche) | C17: Verlag von Jakob Frankel, Regensburg | D17: Regensburg | E17: Topografie / Mehrbild-Lithografie | F17: Gut (Z2) | G17: Farbige Lithografie mit Weinlaub-Rahmung, gelaufen mit 5-Pfennig Bayern-Marke | H17: Ja | I17: 1899 | J17: Regensburg / Straubing / Wiesenfelden, 15.07.1899 | K17: Hochwürden Hochwohlgeboren Herrn Anton Windhager, Pfarrer, Wiesenfelden b. Wörth a.d. Donau | L17: 5 | M17: 10 | N17: =MAX(L17,M17) -> 10 | O17: Im Bestand | P17: Mehrbild, Walhalla, Steinerne Brücke, Jugendstil-Ornamentik
A18: AK-2026-0017 | B18: Regensburg – Moltkeplatz im Schnee (Nachtschneekarte mit Dom) | C18: Hermann Martin, Kunstverlag, Nürnberg (No. 939) | D18: Regensburg | E18: Topografie / Nachtschneekarte | F18: Sehr gut (Z1-2) | G18: Stimmungsvolle Nachtansicht im Schnee mit Sternenhimmel, gelaufen mit 5-Pfennig Bayern-Marke | H18: Ja | I18: 1901 | J18: Regensburg / Straubing / Wiesenfelden, 29.01.1901 | K18: Hochwürden Hochwohlgeboren Herrn Anton Windhager, Pfarrer, Wiesenfelden b. Wörth a.d. Donau | L18: 8 | M18: 15 | N18: =MAX(L18,M18) -> 15 | O18: Im Bestand | P18: Nachtschneekarte, Sternenhimmel, Regensburger Dom, Moltkeplatz
A19: AK-2026-0018 | B19: München – Justizpalast und Treppenhaus | C19: Druck u. Verlag von Louis Glaser, Leipzig (No. 5268) | D19: München | E19: Topografie / Mehrbild-Lithografie | F19: Gut (Z2) | G19: Farbige Litho mit Justizpalast und Prunktreppenhaus, gelaufen mit 5-Pfennig Bayern-Marke | H19: Ja | I19: 1898 | J19: München / Straubing / Wiesenfelden, 02./03.08.1898 | K19: H. Hochwürden Herrn Anton Windhager, Pfarrer, Wiesenfelden über Straubing | L19: 5 | M19: 10 | N19: =MAX(L19,M19) -> 10 | O19: Im Bestand | P19: Justizpalast, Treppenhaus, Louis Glaser Verlag, Mehrbild
A20: AK-2026-0019 | B20: Altenthann – Ortsansicht, Gasthof Gansmeier und Schulhaus | C20: Foto-Elfner, Regensburg, St. Petersweg 19 | D20: Altenthann | E20: Topografie / Mehrbild-Ansichtskarte | F20: Sehr gut (Z1-2) | G20: Mehrbildkarte mit Gasthof Gansmeier, gelaufen mit 6-Pfennig Deutsches Reich Marke | H20: Ja | I20: 1943 | J20: Otterbach / Lupburg, 29.10.1943 | K20: Frl. Gabriele Sauerer in Lupburg, Post Lupburg | L20: 4 | M20: 8 | N20: =MAX(L20,M20) -> 8 | O20: Im Bestand | P20: Altenthann, Gasthof Gansmeier, Mehrbild, Weltkriegszeit 1943
A21: AK-2026-0020 | B21: Regensburg – Walhalla (Ansicht von unten mit den Terrassen) | C21: O. Schleich Nacht., Dresden, Doppeltonlichtdruck (No. 4491) | D21: Regensburg / Donaustauf | E21: Topografie / Echt-Lichtdruck | F21: Gut (Z2) | G21: Einfarbiger Doppelton-Lichtdruck, gelaufen mit Stempel von Regensburg | H21: Ja | I21: 1905 | J21: Regensburg / Parsberg, 03.06.1905 | K21: Herrn Joseph P. Pandarm?, Parsberg | L21: 3 | M21: 7 | N21: =MAX(L21,M21) -> 7 | O21: Im Bestand | P21: Walhalla, Donaustauf, O. Schleich Nacht. Dresden, Lichtdruck
A22: AK-2026-0021 | B22: Regensburg – Panorama mit Postillon und Briefkasten | C22: Verlag von Jakob Frankel, Regensburg | D22: Regensburg | E22: Topografie / Postkarten-Motiv-Lithografie | F22: Gut (Z2) | G22: Farblitho mit Postbote, Pferd und Regensburger Altstadt-Panorama, gelaufen | H22: Ja | I22: 1903 | J22: Nabburg / Oberviechtach / Bernhardswald / Pirkensee, 15./16.10.1903 | K22: An Herrn Joh. Gansmeier, Pirkensee | L22: 6 | M22: 12 | N22: =MAX(L22,M22) -> 12 | O22: Im Bestand | P22: Postillon, Jakob Frankel Verlag, Regensburger Dom, Litho
A23: AK-2026-0022 | B23: Regensburg – Gruss aus Regensburg (Donau-Ansicht mit Wappen) | C23: Verlag von Jakob Frankel, Regensburg (No. 254) | D23: Regensburg | E23: Topografie / Passepartout-Lithografie | F23: Gut (Z2) | G23: Passepartout-Karte mit Reliefprägung, Wappen und Farblitho, gelaufen | H23: Ja | I23: 1902 | J23: Regensburg / Nabburg / Oberviechtach, 23.10.1902 | K23: Herrn Josef Gansmeier, Pirkensee b. Burglengenfeld | L23: 6 | M23: 12 | N23: =MAX(L23,M23) -> 12 | O23: Im Bestand | P23: Passepartout, Wappen, Jakob Frankel Verlag, Donau-Ansicht
... A31: AK-2026-0030 | B31: Ingolstadt – Gruss aus Ingolstadt (Donauansicht mit Brücke) | C31: Chr. Bayerlein jr., Ingolstadt (No. 1240) | D31: Ingolstadt | E31: Topografie / Ansichtskarte | F31: Gut (Z2) | G31: S/W-Ansichtskarte mit Zierrand/Prägung, gelaufen mit Stempel Ingolstadt und Ankunftsstempel Schleiz | H31: Ja | I31: 1901 | J31: Ingolstadt / Schleiz / Plottersdorf, 04.05.1901 | K31: An Herrn Otto Raithel bei Herrn Pastor Dr. Haller, Plottersdorf b. Schleiz (Reuß) | L31: 3.5 | M31: 7 | N31: =MAX(L31,M31) -> 7 | O31: Im Bestand | P31: Ingolstadt, Donau, Bayerlein Verlag, 1901
A32: AK-2026-0031 | B32: Gößweinstein – Gruss aus Gößweinstein, Fränkische Schweiz (Mehrbild-Echtphoto) | C32: Kunstverlagsanstalt F. v. Leistner & Demartin, Muggendorf/Ofr. (12/804) | D32: Gößweinstein | E32: Topografie / Mehrbild-Echtphotokarte | F32: Sehr gut (Z1-2) | G32: S/W-Echtphotokarte mit vielen Ansichten, Wappen/Spruch und gezahntem Rand, ungelaufen | H32: Nein | J32: Unbekannt | K32: Unbekannt | L32: 4 | M32: 8 | N32: =MAX(L32,M32) -> 8 | O32: Im Bestand | P32: Gößweinstein, Fränkische Schweiz, Leistner & Demartin, Mehrbildkarte, Echtphoto
A33: AK-2026-0032 | B33: Burglengenfeld – Naabbrücke mit Burg | C33: Maria Lautenschlager, Schreibwaren, Burglengenfeld (78451) | D33: Burglengenfeld | E33: Topografie / Ansichtskarte | F33: Sehr gut (Z1-2) | G33: S/W-Ansichtskarte der Naabbrücke mit der Burg im Hintergrund, gelaufen mit 6-Pfennig Deutsches-Reich-Marke | H33: Ja | I33: 1941 | J33: Burglengenfeld / Lupburg, 26.06.1941 | K33: Familie Josef Laurer, Lupburg über Parsberg | L33: 4 | M33: 8 | N33: =MAX(L33,M33) -> 8 | O33: Im Bestand | P33: Burglengenfeld, Naabbrücke, Burg, Lautenschlager, Oberpfalz
A34: AK-2026-0033 | B34: Gasthof - Metzgerei „Zum Burgblick“ Burglengenfeld/Opf. | C34: Schwarz-Verlag GmbH, 7832 Kenzingen/Breisgau (Bestell-Nr. 5233 s) | D34: Burglengenfeld / Oberpfalz / Bayern | E34: Burglengenfeld / Gasthof Zum Burgblick / Metzgerei / Gastronomie / Heimatkarte | F34: Ungelaufen / Sehr gut (Z1-2) | G34: Ungelaufene Werbe-Ansichtskarte des Gasthofs und der Metzgerei „Zum Burgblick“ (Familie Peter Sauerer, Naabgasse 7, 8412 Burglengenfeld/Opf.) mit Innen- und Außenansichten | H34: Nein | I34: Keiner | J34: Keiner | K34: Keine | L34: 5 | M34: 10 | N34: =MAX(L34,M34) -> 10 | O34: Im Bestand | P34: Lokale Werbe-Ansichtskarte des Gasthofs Zum Burgblick in Burglengenfeld (Oberpfalz) | Q34: Sehr guter Zustand, minimale Kantenbestoßungen, unbeschrieben, rückseitig unbeschrieben
A35: AK-2026-0034 | B35: Gößweinstein – Höhenkurort Gössweinstein, Blick vom Gernerfels (Echtphoto) | C35: Kunstanstalt E. von Leistner, Muggendorf | D35: Gößweinstein | E35: Topografie / Echtphotokarte | F35: Gut bis Sehr gut (Z2+) | G35: S/W-Echtphotokarte mit Stempel Gössweinstein (500m) vom 17.07.1933, gelaufen | H35: Ja | I35: 1933 | J35: Gößweinstein / Parsberg, 17.07.1933 | K35: Herrn Josef Sauerer, Gasanstaltspächter, Parsberg (Oberpfalz) | L35: 4 | M35: 8 | N35: =MAX(L35,M35) -> 8 | O35: Im Bestand | P35: Gößweinstein, Gernerfels, Leistner, Bromsilber-Abzug, 1933
A36: AK-2026-0035 | B36: Parsberg i. Opf. – Südansicht & Östliche Ansicht (Mehrbild) | C36: Verlag A. Bermüller, Parsberg (439) | D36: Parsberg | E36: Topografie / Mehrbild-Ansichtskarte | F36: Gut (Z2) | G36: S/W-Mehrbildkarte mit Schloss Parsberg, gelaufen mit Stempel Lupburg vom 03.07.1909 | H36: Ja | I36: 1909 | J36: Lupburg / Holnstein b. Berching, 02.07.1909 | K36: Herrn Joseph Sauerer, Gand. Forst. [Gendarmerie-Station / Forstamt], Holnstein b. Berching | L36: 4 | M36: 8 | N36: =MAX(L36,M36) -> 8 | O36: Im Bestand | P36: Parsberg, Oberpfalz, Schloss Parsberg, Bermüller Verlag, 1909
A37: AK-2026-0036 | B37: Amberg Opf. – St. Georgskirche | C37: F. H. Dennerlein, Kunstverlag, Nürnberg (6) | D37: Amberg | E37: Topografie / Ansichtskarte | F37: Gut bis Sehr gut (Z2+) | G37: S/W-Ansichtskarte mit Stempel Amberg vom 18.03.1955 und Notopfer-Marke, gelaufen | H37: Ja | I37: 1955 | J37: Amberg / Lupburg, 18.03.1955 | K37: Gend. Kommissar Josef Sauerer, Lupburg, Kreis Parsberg | L37: 3 | M37: 6 | N37: =MAX(L37,M37) -> 6 | O37: Im Bestand | P37: Amberg, St. Georgskirche, Dennerlein Verlag, 1955, Notopfer Berlin
A38: AK-2026-0037 | B38: Regensburg – Seminar Obermünster, Portal | C38: Unbekannt / Verlagslos | D38: Regensburg | E38: Topografie / Ansichtskarte | F38: Gut bis Sehr gut (Z2+) | G38: S/W-Ansichtskarte mit Stempel Regensburg (Deutsches Reich 6 Pf-Marke), gelaufen | H38: Ja | I38: Unbekannt | J38: Regensburg / Lupburg b. Parsberg | K38: Herrn Jos. Sauerer, Gend. Oberkommissär a. D., Lupburg b. Parsberg | L38: 3 | M38: 6 | N38: =MAX(L38,M38) -> 6 | O38: Im Bestand | P38: Regensburg, Obermünster, Seminar, Portal, Kirche
A39: AK-2026-0038 | B39: Bad Reichenhall – Bayerisches Feuerwehr-Erholungsheim & Predigtstuhl | C39: Martin Herpich, Kunst- u. Verlagsanstalt, München | D39: Bad Reichenhall | E39: Topografie / Ansichtskarte | F39: Gut bis Sehr gut (Z2+) | G39: S/W-Ansichtskarte mit Sonderstempel „Predigtstuhl-Bahn Bad Reichenhall“ und Stempel vom 07.09.1936, gelaufen | H39: Ja | I39: 1936 | J39: Bad Reichenhall / Lupburg b. Parsberg, 07.09.1936 | K39: Frau Lina Sauerer, Lupburg b. Parsberg, Opf. | L39: 4 | M39: 8 | N39: =MAX(L39,M39) -> 8 | O39: Im Bestand | P39: Bad Reichenhall, Feuerwehr-Erholungsheim, Predigtstuhlbahn, Berchtesgadener Land, 1936
A40: AK-2026-0039 | B40: Linz a. D. – Pöstlingberg (Fliegeraufnahme / Luftbild) | C40: Österreichische Luftbild-Industrie Bad Ischl (896) | D40: Linz (Österreich) | E40: Topografie / Luftbild-Ansichtskarte | F40: Gut bis Sehr gut (Z2+) | G40: Sepia-Luftbildkarte mit Stempel vom August 1940, gelaufen | H40: Ja | I40: 1940 | J40: Linz / Lupburg b. Parsberg, 01.08.1940 | K40: Familie Jos. Sauerer, Gend. Oberkommissär a. D., Lupburg b. Parsberg u. Regensburg bey. Oberpfg. | L40: 3 | M40: 6 | N40: =MAX(L40,M40) -> 6 | O40: Im Bestand | P40: Linz, Pöstlingberg, Österreich, Luftbild, Fliegeraufnahme, 1940
A41: AK-2026-0040 | B41: Donaustauf bei Regensburg – Walhalla | C41: Unbekannt / Verlagslos | D41: Donaustauf | E41: Topografie / Ansichtskarte | F41: Gut (Z2) | G41: S/W-Ansichtskarte mit Stempel Donaustauf, gelaufen | H41: Ja | I41: Unbekannt | J41: Donaustauf / [Empfängerort unklar] | K41: Herrn Josef Sauerer, [Gendarmerie / Kumpfmühl bei Regensburg] | L41: 3 | M41: 6 | N41: =MAX(L41,M41) -> 6 | O41: Im Bestand | P41: Donaustauf, Walhalla, Regensburg, Monumentalbau, Ruhmeshalle
A42: AK-2026-0041 | B42: Donaustauf – Walhalla (Tempel deutscher Ehren) | C42: Hermann Martin, Kunstverlag, Nürnberg (1033) | D42: Donaustauf | E42: Topografie / Litho-Ansichtskarte | F42: Gut bis Sehr gut (Z2+) | G42: Kolorierte Ansichtskarte mit Stempel Fürth (Bayern) und Ankunftsstempel Velburg vom August 1904, gelaufen | H42: Ja | I42: 1904 | J42: Fürth (Bayern) / Velburg, 03.08.1904 | K42: Herrn Joseph Sauerer, kgl. Gendarm, Velburg | L42: 4 | M42: 8 | N42: =MAX(L42,M42) -> 8 | O42: Im Bestand | P42: Donaustauf, Walhalla, König Ludwig I., Koloriert, Litho, 1904, Velburg, Fürth
A43: AK-2026-0042 | B43: Parsberg – Schloßaufgang | C43: Verlag: Buchhandlung L. Bermüller, Parsberg (P 5038 42) | D43: Parsberg | E43: Topografie / Ansichtskarte | F43: Sehr gut (Z1- bis Z2+) | G43: S/W-Ansichtskarte mit Schloss Parsberg und Aufgang, ungelaufen | H43: Nein | J43: Unbekannt | K43: Unbekannt / Ohne Empfänger | L43: 2 | M43: 5 | N43: =MAX(L43,M43) -> 5 | O43: Im Bestand | P43: Parsberg, Schloßaufgang, Zwiebeltürme, Schloss, Bermüller Verlag, Oberpfalz
A44: AK-2026-0043 | B44: Regensburg – Am Wiedfang | C44: Unbekannt / Verlagslos | D44: Regensburg | E44: Topografie / Ansichtskarte | F44: Gut bis Sehr gut (Z2+) | G44: S/W-Ansichtskarte mit Stempel Regensburg vom Juli (Deutsches Reich), gelaufen | H44: Ja | I44: Unbekannt | J44: Regensburg / Velburg b. Parsberg (bzw. geändert) | K44: Herrn Joseph Sauerer, Gend. Oberkommissär a. D., Velburg b. Parsberg | L44: 3 | M44: 6 | N44: =MAX(L44,M44) -> 6 | O44: Im Bestand | P44: Regensburg, Am Wiedfang, Brunnen, Altstadt, historisch
A45: AK-2026-0044 | B45: Lupburg – Neue Pfarrkirche (Innenraum / Altarraum) | C45: Photo-Perras, Photobedarf, Parsberg (f 17) | D45: Lupburg | E45: Topografie / Ansichtskarte | F45: Sehr gut (Z1- bis Z2+) | G45: S/W-Ansichtskarte vom Kircheninneren, ungelaufen | H45: Nein | J45: Unbekannt | K45: Unbekannt / Ohne Empfänger | L45: 2 | M45: 5 | N45: =MAX(L45,M45) -> 5 | O45: Im Bestand | P45: Lupburg, Neue Pfarrkirche, Innenansicht, Altar, Kanzel, Photo-Perras, Parsberg, Oberpfalz
A46: AK-2026-0045 | B46: München – Königl. Hofbräuhaus (Gruss aus München) | C46: Verlag & Druck Kunst-Anstalt Rosenblatt, Frankfurt a. M. (4762) | D46: München | E46: Topografie / Litho-Ansichtskarte | F46: Gut bis Sehr gut (Z2+) | G46: Kolorierte Litho-Ansichtskarte mit Stempel Muenchen vom 18.12.1900 und Ankunftsstempel Wiesenfelden, gelaufen | H46: Ja | I46: 1900 | J46: Muenchen / Wiesenfelden, 18.12.1900 | K46: Wohlgeb. Herrn Andreas Windberger, Kgl. Pfarrer Wohlgeboren, Wiesenfelden b. Thierhaupten (bzw. Vilsbiburg / Opf.) | L46: 4 | M46: 8 | N46: =MAX(L46,M46) -> 8 | O46: Im Bestand | P46: München, Hofbräuhaus, Gruss aus München, Bierkrug, Litho, koloriert, 1900, Wiesenfelden, Rosenblatt Verlag
A47: AK-2026-0046 | B47: Rosenheim – Gruss aus Rosenheim (Alpenpanorama) | C47: Verlag Arno Loth, Rosenheim (4367) | D47: Rosenheim | E47: Topografie / Litho-Ansichtskarte | F47: Gut bis Sehr gut (Z2+) | G47: Kolorierte Litho-Ansichtskarte mit Stempel Rosenheim und Ankunftsstempel Wiesenfelden vom 29.08.1903, gelaufen | H47: Ja | I47: 1903 | J47: Rosenheim / Wiesenfelden, 28./29.08.1903 | K47: Hochwürdigen Herrn Pfarrer Al. Windbarger, Fräulein in Wiesenfelden (Thierhaupten / Opf.) | L47: 4 | M47: 8 | N47: =MAX(L47,M47) -> 8 | O47: Im Bestand | P47: Rosenheim, Gruss aus Rosenheim, Alpen, Panorama, Litho, koloriert, 1903, Arno Loth Verlag
A48: AK-2026-0047 | B48: Regensburg – Der Dom (107m, Westfassade) | C48: Georg Deinzer, Nürnberg (No. 174) | D48: Regensburg | E48: Topografie / Ansichtskarte | F48: Gut bis Sehr gut (Z2+) | G48: S/W-Ansichtskarte mit Stempel Regensburg vom 10.2.1939 (Deutsches Reich), gelaufen | H48: Ja | I48: 1939 | J48: Regensburg / Lupburg, 10.02.1939 | K48: Familie Josef Sauerer, Gend. Oberkommissär a. D., Lupburg über Parsberg | L48: 2.5 | M48: 5.5 | N48: =MAX(L48,M48) -> 5.5 | O48: Im Bestand | P48: Regensburg, Dom, Westfassade, Kathedrale, 107m, Georg Deinzer, Nürnberg, 1939
A49: AK-2026-0048 | B49: Regensburg – Haus Thurn und Taxis (Jubiläums-Ansichtskarte 1748–1898) | C49: Verlag von Jakob Frankel, Regensburg | D49: Regensburg | E49: Topografie / Historische Ansichtskarte | F49: Gut bis Sehr gut (Z2+) | G49: Historische Litho-Ansichtskarte mit Stempel Oberviechtach vom 10.1.1899, gelaufen | H49: Ja | I49: 1899 | J49: Regensburg / Oberviechtach, 10.01.1899 | K49: Herrn Joseph Sauerer, Gendarm in Oberviechtach, Post daselbst | L49: 3 | M49: 6.5 | N49: =MAX(L49,M49) -> 6.5 | O49: Im Bestand | P49: Regensburg, Thurn und Taxis, Jubiläum, 1748, 1898, Fürst Albert, Fürstin Margarethe, Post, Jakob Frankel, 1899
A50: AK-2026-0049 | B50: München – Marienplatz gegen altes Rathaus (Flaggenschmuck) | C50: F. J. H. – M. (Nr. 218) | D50: München | E50: Topografie / Ansichtskarte | F50: Gut bis Sehr gut (Z2+) | G50: Kolorierte Ansichtskarte mit Stempel vom 10.12.1934 (Deutsches Reich), gelaufen | H50: Ja | I50: 1934 | J50: München / Parsberg (Opf.), 10.12.1934 | K50: Familie Sauerer, Oberkommissär, Parsberg (Opf.) | L50: 2.5 | M50: 5.5 | N50: =MAX(L50,M50) -> 5.5 | O50: Im Bestand | P50: München, Marienplatz, altes Rathaus, Flaggenschmuck, Straßenbahn, 1934, Oberpfalz
A51: AK-2026-0050 | B51: Metz – Gruss aus Metz (Theater, Paradeplatz, Kathedrale) | C51: Druck u. Verlag v. Louis Glaser, Leipzig | D51: Metz (Elsaß-Lothringen) | E51: Topografie / Mehrfeld-Litho | F51: Gut (Z2) | G51: Litho-Ansichtskarte mit Stempel Metz vom 20.2.1899 (Deutsche Reichspost), gelaufen | H51: Ja | I51: 1899 | J51: Metz / Reiting (Donaustauf), 20.02.1899 | K51: Herrn Joseph Sauerer, Ökonom in Reiting, Post Donaustauf (Oberpfalz) | L51: 3 | M51: 6.5 | N51: =MAX(L51,M51) -> 6.5 | O51: Im Bestand | P51: Metz, Gruss aus Metz, Theater, Paradeplatz, Stadthaus, Kathedrale, Louis Glaser, Leipzig, 1899
A52: AK-2026-0051 | B52: Seubersdorf – Schulhaus | C52: Unbekannt (Nr. 7518) | D52: Seubersdorf (Oberpfalz) | E52: Topografie / Ansichtskarte | F52: Sehr gut (Z1- bis Z2) | G52: Kolorierte Ansichtskarte, ungelaufen, unbeschrieben | H52: Nein | I52: Ca. 1910–1920 | J52: – | K52: – | L52: 3 | M52: 14 | N52: =MAX(L52,M52) -> 14 | O52: Im Bestand | P52: Seubersdorf, Schulhaus, Schulgebäude, Oberpfalz, Steinbau, 7518
A53: AK-2026-0052 | B53: Nürnberg – Gruss aus Nürnberg (Burg) | C53: Verlag von Kaspar Bader, München | D53: Nürnberg | E53: Topografie / Ansichtskarte | F53: Gut (Z2) | G53: Historische Ansichtskarte mit Stempel Marktredwitz vom 15.07.1900, gelaufen | H53: Ja | I53: 1900 | J53: Nürnberg / Marktredwitz, 15.07.1900 | K53: Herrn Lorenz Thoma, Maschinenfabrik J. Beckstein, Marktredwitz (Oberfranken) | L53: 2.5 | M53: 5.5 | N53: =MAX(L53,M53) -> 5.5 | O53: Im Bestand | P53: Nürnberg, Burg, Gruss aus Nürnberg, Kaspar Bader, München, 1900, Marktredwitz, Oberfranken
A54: AK-2026-0053 | B54: München – Saal im kgl. Hofbräuhaus | C54: Photochrom No 8 (Photoglob Zürich) | D54: München | E54: Topografie / Ansichtskarte | F54: Gut (Z2) | G54: Farbige Litho-Ansichtskarte mit Stempel München vom 11.08.1900, gelaufen | H54: Ja | I54: 1900 | J54: München / [Empfänger in Wörthstraße 2], 11.08.1900 | K54: Herrn Alois Raster, Gymnasiast in Wörthstraße 2 | L54: 3 | M54: 6.5 | N54: =MAX(L54,M54) -> 6.5 | O54: Im Bestand | P54: München, Hofbräuhaus, Festsaal, Saal, Photoglob Zürich, 1900, Wörthstraße
A55: AK-2026-0054 | B55: Tegernsee – Gesamtansicht mit See und Bergen | C55: Unbekannt / Verlagslos | D55: Tegernsee | E55: Topografie / Ansichtskarte | F55: Gut bis Sehr gut (Z2+) | G55: Kolorierte Ansichtskarte mit Stempel vom 8.6.1907 und Ankunftsstempel Schleiz, gelaufen | H55: Ja | I55: 1907 | J55: Tegernsee / Vettersdorf (Schleiz), 08./09.06.1907 | K55: Herrn Otto Raithel bei Herrn Repor. Dr. Haller, Vettersdorf b. Schleiz (Reuß j.L.) | L55: 3 | M55: 6.5 | N55: =MAX(L55,M55) -> 6.5 | O55: Im Bestand | P55: Tegernsee, See, Alpen, Panorama, koloriert, 1907, Vettersdorf, Schleiz
A56: AK-2026-0055 | B56: Oberpfraudorf – Gruß aus Oberpfraudorf (Schreinerei & Gemischtwaren Krottner) | C56: Verlag: Schreinerei u. Gemischtwaren von Krottner (Nr. 6923) | D56: Oberpfraudorf (Oberpfalz) | E56: Topografie / Ansichtskarte | F56: Gut bis Sehr gut (Z2+) | G56: S/W-Ansichtskarte mit Ortsansicht und Laden, ungelaufen | H56: Nein | J56: Unbekannt | K56: Unbekannt / Ohne Empfänger | L56: 4 | M56: 9 | N56: =MAX(L56,M56) -> 9 | O56: Im Bestand | P56: Oberpfraudorf, Schreinerei, Gemischtwaren, Krottner, Persil, Ortsansicht, Oberpfalz, 6923
A57: AK-2026-0056 | B57: Regensburg – Steinerne Brücke, Salzspeicher und Dom | C57: Kosmos-Verlag (Franckh-Verlag), Stuttgart (Nr. 19639-86a) | D57: Regensburg | E57: Topografie / Echtfoto-Ansichtskarte | F57: Sehr gut (Z1- bis Z2+) | G57: S/W-Echte-Fotokarte, ungelaufen, unbeschrieben | H57: Nein | J57: Unbekannt | K57: Unbekannt / Ohne Empfänger | L57: 2.5 | M57: 5.5 | N57: =MAX(L57,M57) -> 5.5 | O57: Im Bestand | P57: Regensburg, Steinerne Brücke, Salzspeicher, Dom, Donau, Kosmos Verlag, Echtfoto
A58: AK-2026-0057 | B58: Regensburg – Mehrfelderkarte (Steinerne Brücke, Walhalla, Donaupartie, Adolf-Hitler-Brücke) | C58: Unbekannt / Verlagslos (REGENSBURG) | D58: Regensburg | E58: Topografie / Mehrfelder-Ansichtskarte | F58: Sehr gut (Z1- bis Z2+) | G58: S/W-Mehrfelder-Ansichtskarte, ungelaufen, unbeschrieben | H58: Nein | J58: Unbekannt | K58: Unbekannt / Ohne Empfänger | L58: 2.5 | M58: 5 | N58: =MAX(L58,M58) -> 5 | O58: Im Bestand | P58: Regensburg, Mehrfelderkarte, Steinerne Brücke, Walhalla, Donaupartie, Adolf-Hitler-Brücke, Nibelungenbrücke
A59: AK-2026-0058 | B59: Altötting – Kapellplatz und Basilika | C59: Verlag V. Gabriel Wallherr, Altötting | D59: Altötting | E59: Topografie / Ansichtskarte | F59: Gut (Z2) | G59: S/W-Ansichtskarte als Drucksache mit Stempel Altötting und Ankunftsstempel Wiesenfelden vom 10.06.1903, gelaufen | H59: Ja | I59: 1903 | J59: Altötting / Wiesenfelden, 09./10.06.1903 | K59: Wohlge. Frau Glosbauer, Theil b. Neumarkt/Opf. (bzw. Wiesenfelden) | L59: 3 | M59: 7 | N59: =MAX(L59,M59) -> 7 | O59: Im Bestand | P59: Altötting, Kapellplatz, Basilika, Wallherr Verlag, Drucksache, 1903, Oberpfalz
A60: AK-2026-0059 | B60: Obersalzberg – Mehrfelderkarte mit historischen Motiven (Hitler-Haus, Kehlsteinhaus, Göring-Haus etc.) | C60: Ansichtskartenfabrik Schöning & Co., Lübeck (Bgd 424-N) | D60: Obersalzberg (Berchtesgaden) | E60: Topografie / Mehrfelder-Ansichtskarte | F60: Gut (Z2) | G60: S/W-Mehrfelder-Ansichtskarte mit Stempel Bad Reichenhall (1950er Jahre), gelaufen | H60: Ja | I60: Ca. 1955 | J60: Obersalzberg / Erlangen, ca. 1950er | K60: Familie Gustav Adolph, Erlangen, Am Röthelheim 5 | L60: 3 | M60: 7 | N60: =MAX(L60,M60) -> 7 | O60: Im Bestand | P60: Obersalzberg, Berchtesgaden, Hitler-Haus, Kehlsteinhaus, Göring-Haus, SS-Kasernen, Schöning Lübeck, 1950er, Erlangen
A61: AK-2026-0060 | B61: Lupburg – Gruss aus Lupburg (Ortsansicht mit Burg) | C61: Verlag von Joh. Landfried, Lupburg | D61: Lupburg (Oberpfalz) | E61: Topografie / Soldatenkarte | F61: Gut bis Sehr gut (Z2+) | G61: S/W-Ansichtskarte als Soldatenkarte mit Stempel Lupburg vom 1.2.1909, gelaufen | H61: Ja | I61: 1909 | J61: Lupburg / Grünstaude (Hemau), 01.02.1909 | K61: Herrn Joseph Sauerer, Gendarm, Grünstaude Post Hemau | L61: 5 | M61: 13 | N61: =MAX(L61,M61) -> 13 | O61: Im Bestand | P61: Lupburg, Burg, Soldatenkarte, Joh. Landfried, 1909, Oberpfalz, Grünstaude, Hemau
A62: AK-2026-0061 | B62: Vichtenstein a. Donau – Burg Vichtenstein | C62: Alleinverlag A. Art, Passau (Nr. 24001) | D62: Vichtenstein (Österreich / Oberösterreich) | E62: Topografie / Ansichtskarte | F62: Sehr gut (Z1- bis Z2) | G62: S/W-Ansichtskarte mit Stempel Passau vom 1. Sep. (1930er Jahre), gelaufen | H62: Ja | I62: Ca. 1930–1938 | J62: Vichtenstein / Passau, 01.09. | K62: Unbekannt / Ohne Empfänger (ungeschriebener Textteil) | L62: 2.5 | M62: 5.5 | N62: =MAX(L62,M62) -> 5.5 | O62: Im Bestand | P62: Vichtenstein, Donau, Burg Vichtenstein, Österreich, Passau, A. Art, 24001
A63: AK-2026-0062 | B63: München – Theatinerkirche und Feldherrnhalle | C63: Unbekannt / Verlagslos | D63: München | E63: Topografie / Ansichtskarte | F63: Gut (Z2) | G63: Kolorierte Ansichtskarte mit Stempel Wiesenfelden vom 22.07.1903, gelaufen | H63: Ja | I63: 1903 | J63: München / Wiesenfelden, 21./22.07.1903 | K63: Hochwürden Herrn Anton Minchinger, Pfarrer, Fördergut / Wiesenfelden, Postpfl. Rodingersdorf | L63: 3 | M63: 7 | N63: =MAX(L63,M63) -> 7 | O63: Im Bestand | P63: München, Theatinerkirche, Feldherrnhalle, koloriert, 1903, Wiesenfelden, Rodingersdorf
A64: AK-2026-0063 | B64: München – Maximilianskirche | C64: Ottmar Zieher, München | D64: München | E64: Topografie / Ansichtskarte | F64: Gut (Z2) | G64: S/W-Ansichtskarte mit Stempel München und Ankunftsstempel Wiesenfelden vom 06.07.1904, gelaufen | H64: Ja | I64: 1904 | J64: München / Wiesenfelden, 05./06.07.1904 | K64: Hochwürden H. H. Anton Minchinger, Pfarrer, Gehöft bzw. Wiesenfelden, Postpfl. Rodingersdorf | L64: 3 | M64: 7 | N64: =MAX(L64,M64) -> 7 | O64: Im Bestand | P64: München, Maximilianskirche, Ottmar Zieher, Isar, Kirche, 1904, Wiesenfelden, Rodingersdorf
A65: AK-2026-0064 | B65: München – Prinzregenten-Theater | C65: E. Männer, München (Nr. 96) | D65: München | E65: Topografie / Ansichtskarte | F65: Gut (Z2) | G65: Kolorierte Ansichtskarte mit Stempel Schleiz vom 13.08.1902, gelaufen | H65: Ja | I65: 1902 | J65: München / Vettersdorf (Schleiz), 12./13.08.1902 | K65: Herrn Otto Raithel bei Herrn Repor. Dr. Haller, Vettersdorf b. Schleiz (Reuß) | L65: 3 | M65: 7 | N65: =MAX(L65,M65) -> 7 | O65: Im Bestand | P65: München, Prinzregenten-Theater, Theater, E. Männer, koloriert, 1902, Vettersdorf, Schleiz
A66: AK-2026-0065 | B66: München – Frauenkirche | C66: Unbekannt / Verlagslos | D66: München | E66: Topografie / Ansichtskarte | F66: Gut (Z2) | G66: Kolorierte Ansichtskarte mit Stempel München und Ankunftsstempel Marktredwitz vom 09.11.1903, gelaufen | H66: Ja | I66: 1903 | J66: München / Marktredwitz, 08./09.11.1903 | K66: Herrn Lorenz Thomae, Eisendreher in Marktredwitz, Fa. Beckstein | L66: 3 | M66: 7 | N66: =MAX(L66,M66) -> 7 | O66: Im Bestand | P66: München, Frauenkirche, Kirche, koloriert, 1903, Marktredwitz, Beckstein
A67: AK-2026-0066 | B67: München – Neues Rathaus | C67: Verlag Franz Joseph Huber, München (No. 358) | D67: München | E67: Topografie / Ansichtskarte | F67: Gut bis Sehr gut (Z2+) | G67: Kolorierte Ansichtskarte mit Auslandsstempel nach London vom 13.11.1911, gelaufen | H67: Ja | I67: 1911 | J67: München / London, 13.11.1911 | K67: Herrn Otto Raithel c/o Herren Hartgen & Co., Noble House 35/37 Noble Street, London E.C. | L67: 4 | M67: 10 | N67: =MAX(L67,M67) -> 10 | O67: Im Bestand | P67: München, Neues Rathaus, Marienplatz, Franz Joseph Huber, Ausland, London, 1911
A68: AK-2026-0067 | B68: Bayreuth – Röhrensee mit Springbrunnen | C68: Ottmar Zieher, München (Z 5278) | D68: Bayreuth | E68: Topografie / Ansichtskarte | F68: Sehr gut (Z1) | G68: Heliokolorkarte, ungelaufen, unbeschrieben | H68: Nein | J68: Unbekannt | K68: Unbekannt / Ohne Empfänger | L68: 2.5 | M68: 5.5 | N68: =MAX(L68,M68) -> 5.5 | O68: Im Bestand | P68: Bayreuth, Röhrensee, Springbrunnen, See, Ottmar Zieher, Heliokolor, Z 5278
A69: AK-2026-0068 | B69: Bayreuth – Justizpalast | C69: Verlag P. H. B. 25 | D69: Bayreuth | E69: Topografie / Ansichtskarte | F69: Gut (Z2) | G69: S/W-Ansichtskarte mit Stempel Bayreuth vom 30.04.1915, gelaufen | H69: Ja | I69: 1915 | J69: Bayreuth / Hof, 30.04.1915 | K69: Herrn Otto Raithel, Bankbuchhalter in Hof, Kirchhof 11 | L69: 3 | M69: 7 | N69: =MAX(L69,M69) -> 7 | O69: Im Bestand | P69: Bayreuth, Justizpalast, Gebäude, P.H.B. 25, 1915, Hof, Oberfranken
A70: AK-2026-0069 | B70: Nürnberg – Panorama vom Sebaldusturm | C70: Hermann Martin, Kunstverlag, Nürnberg | D70: Nürnberg | E70: Topografie / Ansichtskarte | F70: Gut (Z2) | G70: S/W-Ansichtskarte mit Stempel Nürnberg vom 26.02.1909, gelaufen | H70: Ja | I70: 1909 | J70: Nürnberg / Marktredwitz, 26.02.1909 | K70: Herrn Otto Raithel, Volontär in Marktredwitz, Pflegstätte b. Herrn Carl Schmidt, Bankgeschäft | L70: 3 | M70: 7 | N70: =MAX(L70,M70) -> 7 | O70: Im Bestand | P70: Nürnberg, Panorama, Sebaldusturm, Kaiserburg, Altstadt, Hermann Martin, 1909, Marktredwitz, Carl Schmidt
A71: AK-2026-0070 | B71: Oberammergau – Passionstheater 1900 (Blick in den Zuschauerraum) | C71: Verlag von Carl Aug. Seyfried & Comp., München | D71: Oberammergau | E71: Topografie / Kulturgeschichte | F71: Gut bis Sehr gut (Z2+) | G71: S/W-Ansichtskarte mit Stempel Kohlgrub und Ankunftsstempel Hof a. Saale vom 30.06.1903, gelaufen | H71: Ja | I71: 1903 | J71: Kohlgrub / Hof (Saale), 29./30.06.1903 | K71: Herrn Otto u. Frl. Anna Raithel, Hof a. Oberfranken, Kirchhofstraße 7 | L71: 4 | M71: 10 | N71: =MAX(L71,M71) -> 10 | O71: Im Bestand | P71: Oberammergau, Passionstheater, 1900, Zuschauerraum, Carl Aug. Seyfried, Kohlgrub, Hof, Oberfranken
A72: AK-2026-0071 | B72: München – Bavaria und Ruhmeshalle | C72: Kunstverlag J. Silberstein, München (No. 2609) | D72: München | E72: Topografie / Ansichtskarte | F72: Gut (Z2) | G72: Kolorierte Ansichtskarte mit Stempel München und Ankunftsstempel Schleiz vom 05.05.1901, gelaufen | H72: Ja | I72: 1901 | J72: München / Vettersdorf (Schleiz), 04./05.05.1901 | K72: Herrn Otto Raithel bei Herrn Repor. Dr. Haller, Vettersdorf b. Schleiz (Reuß) | L72: 3 | M72: 7 | N72: =MAX(L72,M72) -> 7 | O72: Im Bestand | P72: München, Bavaria, Ruhmeshalle, Theresienhöhe, J. Silberstein, koloriert, 1901, Vettersdorf, Schleiz
A73: AK-2026-0072 | B73: München – Maximiliansbrücke mit Maximilianeum | C73: Ottmar Zieher, München (W.H.D. 8902 b) | D73: München | E73: Topografie / Ansichtskarte | F73: Gut (Z2) | G73: S/W-Ansichtskarte nach New York gelaufen, mit US-Stempel Station T vom 05.12.1911, gelaufen | H73: Ja | I73: 1911 | J73: München / New York, USA, 05.12.1911 | K73: Herrn Otto Raithel (durchgestrichen: Mrs. Malony), 231 Lenox Ave, New York, U.S.A. | L73: 4 | M73: 10 | N73: =MAX(L73,M73) -> 10 | O73: Im Bestand | P73: München, Maximiliansbrücke, Maximilianeum, Isar, Ottmar Zieher, 1911, New York, USA, Export
A74: AK-2026-0073 | B74: Nürnberg – Königstrasse mit Künstlerhaus | C74: Fr. Riegel, Kunstverlagsanstalt, Nürnberg (Nr. 708) | D74: Nürnberg | E74: Topografie / Ansichtskarte | F74: Sehr gut (Z1-) | G74: S/W-Ansichtskarte mit Straßenbahn und Künstlerhaus, ungelaufen | H74: Nein | I74: ca. 1910 | J74: Unbekannt | K74: Unbekannt | L74: 2.5 | M74: 6 | N74: =MAX(L74,M74) -> 6 | O74: Im Bestand | P74: Nürnberg, Königstraße, Künstlerhaus, Straßenbahn, Fr. Riegel, um 1910, ungelaufen
A75: AK-2026-0074 | B75: Dresden – Postplatz | C75: Verlag D. Kröner (Nr. 263) | D75: Dresden | E75: Topografie / Zeitgeschichte 1939-1945 | F75: Gut (Z2) | G75: S/W-Ansichtskarte mit Feldpost- und Poststempel Klotzsche vom 25.06.1943, gelaufen | H75: Ja | I75: 1943 | J75: Dresden / Lupburg, 24./25.06.1943 | K75: Familie Joseph Laucher, Gend.-Oberkommissar, Lupburg-Opf., Strecke Nürnberg-Regensburg | L75: 4 | M75: 9 | N75: =MAX(L75,M75) -> 9 | O75: Im Bestand | P75: Dresden, Postplatz, 1943, Feldpost, D. Kröner, Lupburg, Oberpfalz
A76: AK-2026-0075 | B76: Ansbach – Mehrbild-Ansichtskarte (9 Motive) | C76: Verlag Fritz Lauterbach, Fürth i. Bay. (Frila-Karte 400/2/61) | D76: Ansbach | E76: Topografie / Mehrbildkarte | F76: Sehr gut (Z1-) | G76: S/W-Mehrbild-Ansichtskarte mit Schloss, Gumbertuskirche, Hofgarten etc., ungelaufen | H76: Nein | I76: ca. 1950–1960 | J76: Unbekannt | K76: Unbekannt | L76: 2 | M76: 5 | N76: =MAX(L76,M76) -> 5 | O76: Im Bestand | P76: Ansbach, Mehrbildkarte, Schloss, Hofgarten, Gumbertuskirche, Fritz Lauterbach, Fürth, ungelaufen
A77: AK-2026-0076 | B77: Passau – Festung Oberhaus | C77: Verlag R 4743 | D77: Passau | E77: Topografie / Ansichtskarte | F77: Gut (Z2) | G77: S/W-Ansichtskarte mit Stempel Passau vom 28.07.1911, gelaufen | H77: Ja | I77: 1911 | J77: Passau / Regensburg, 28./29.07.1911 | K77: Herrn Johann Daner sen., Regensburg, Löffelgasse 28 1/3 | L77: 3 | M77: 7 | N77: =MAX(L77,M77) -> 7 | O77: Im Bestand | P77: Passau, Festung Oberhaus, Donau, R 4743, 1911, Regensburg, Löffelgasse
A78: AK-2026-0077 | B78: Metten – Kloster und Gesamtansicht | C78: Verlag v. Wolfgang Wennig, Metten | D78: Metten | E78: Topografie / Ansichtskarte | F78: Gut (Z2) | G78: Farbige Litho/Ansichtskarte mit Poststempel vom 04.04.1922, gelaufen | H78: Ja | I78: 1922 | J78: Metten / Lupburg, 04.04.1922 | K78: Maria & Anna Laucher, Lupburg b. Parsberg, Opf. | L78: 3 | M78: 7 | N78: =MAX(L78,M78) -> 7 | O78: Im Bestand | P78: Metten, Kloster, Abtei, Niederbayern, Wolfgang Wennig, 1922, Lupburg, Oberpfalz
A79: AK-2026-0078 | B79: München – Frauenkirche von der Michaeliskirche | C79: Dr. Trenkler & Co., Leipzig (Nr. 432) | D79: München | E79: Topografie / Ansichtskarte | F79: Gut (Z2) | G79: S/W-Ansichtskarte mit Stempel München vom 10.08.1899, gelaufen | H79: Ja | I79: 1899 | J79: München / Straubing, 10./11.08.1899 | K79: Herrn Anton Rinhagger, Lehrer, Kirchroth, Post Hunderdorf | L79: 4 | M79: 8 | N79: =MAX(L79,M79) -> 8 | O79: Im Bestand | P79: München, Frauenkirche, Dr. Trenkler, Leipzig, 1899, Straubing, Kirchroth
A80: AK-2026-0079 | B80: Gruss aus Regensburg – St. Theresienkirche in Kumpfmühl | C80: Gez. Joh. Graf, Regensburg (Nr. 2928) | D80: Regensburg-Kumpfmühl | E80: Topografie / Litho-Ansichtskarte | F80: Gut (Z2) | G80: Farbige Litho-Ansichtskarte mit Stempel Regensburg vom 12.07.1902, gelaufen | H80: Ja | I80: 1902 | J80: Regensburg / Wiesenfelden, 12.07.1902 | K80: Herrn Anton Windhager, Lehrer, Wiesenfelden | L80: 4 | M80: 8 | N80: =MAX(L80,M80) -> 8 | O80: Im Bestand | P80: Regensburg, Kumpfmühl, St. Theresienkirche, Joh. Graf, 1902, Wiesenfelden
A81: AK-2026-0080 | B81: Eger – Mehrbild-Ansichtskarte (Historische Stadtansichten) | C81: Unbekannter Verlag (JZE M2) | D81: Eger (Cheb) | E81: Topografie / Zeitgeschichte 1939-1945 | F81: Gut (Z2) | G81: S/W-Mehrbild-Ansichtskarte mit Stempel Eger vom 27.11.1939, gelaufen | H81: Ja | I81: 1939 | J81: Eger / Regensburg, 27.11.1939 | K81: Herrn W. Daner, stud. litt., Regensburg, Heiliggeistgasse 7 | L81: 4 | M81: 9 | N81: =MAX(L81,M81) -> 9 | O81: Im Bestand | P81: Eger, Cheb, Mehrbildkarte, Kaiserburg, Adolf-Hitler-Platz, 1939, Regensburg, Heiliggeistgasse
A82: AK-2026-0081 | B82: Regensburg – Adolf-Hitler-Brücke (Nibelungenbrücke) | C82: Unbekannter Verlag | D82: Regensburg | E82: Topografie / Zeitgeschichte 1939-1945 | F82: Sehr gut (Z1-) | G82: S/W-Ansichtskarte der Donaubrücke und Schottenheimsiedlung, ungelaufen | H82: Nein | I82: ca. 1938–1940 | J82: Unbekannt | K82: Unbekannt | L82: 3 | M82: 7 | N82: =MAX(L82,M82) -> 7 | O82: Im Bestand | P82: Regensburg, Nibelungenbrücke, Adolf-Hitler-Brücke, Donau, Schottenheimsiedlung, ungelaufen
A83: AK-2026-0082 | B83: Regensburg a. d. Donau – Blick auf den Dom | C83: Verlag Schöning & Co., Lübeck (Nr. 24903) | D83: Regensburg | E83: Topografie / Ansichtskarte | F83: Gut (Z2) | G83: S/W-Ansichtskarte mit Stempel Regensburg vom 07.08.1939, gelaufen | H83: Ja | I83: 1939 | J83: Regensburg / Borna, 07.08.1939 | K83: Familie Georg Schenk, Borna b. Leipzig, Wilhem-Eichroth-Str. 40 | L83: 3 | M83: 7 | N83: =MAX(L83,M83) -> 7 | O83: Im Bestand | P83: Regensburg, Dom, Steinerne Brücke, Donau, Schöning & Co., Lübeck, 1939, Borna
A84: AK-2026-0083 | B84: München – Isarpartie mit Maximilianskirche | C84: Unbekannter Verlag | D84: München | E84: Topografie / Zeitgeschichte 1939-1945 | F84: Gut (Z2) | G84: S/W-Ansichtskarte mit Stempel München Hauptstadt der Bewegung vom 25.11.1942, gelaufen | H84: Ja | I84: 1942 | J84: München / Feldkirchen-Westerham, 25.11.1942 | K84: Herrn Joh. Leder, Oberroth b. Feldkirchen, Feldkirchen-Westerham | L84: 4 | M84: 8 | N84: =MAX(L84,M84) -> 8 | O84: Im Bestand | P84: München, Isarpartie, Maximilianskirche, Alpen, 1942, Feldkirchen-Westerham, Zensurstempel
A85: AK-2026-0084 | B85: Prinz Regent Luitpold von Bayern – Jubiläums-Postkarte 1821–1911 | C85: Oscar Consée, München / Entwurf: W. Diez (1910) | D85: München / Bayern | E85: Künstlerkarte / Jubiläum / Monarchie | F85: Sehr gut (Z1-) | G85: Farbige Künstler-Wertstempelkarte mit eingedruckter 5-Pfennig-Marke Bayern, ungelaufen | H85: Nein | I85: 1911 | J85: Unbekannt | K85: Unbekannt | L85: 8 | M85: 18 | N85: =MAX(L85,M85) -> 18 | O85: Im Bestand | P85: Prinz Regent Luitpold, Bayern, 1821-1911, 90. Geburtstag, Wilhelm von Diez, Oscar Consée, ungelaufen
A86: AK-2026-0085 | B86: Prinz Regent Luitpold von Bayern – Jubiläums-Postkarte mit Mädchen (1911) | C86: Oscar Consée, München / Entwurf: W. Diez | D86: München / Bayern | E86: Künstlerkarte / Jubiläum / Monarchie | F86: Sehr gut (Z1-) | G86: Farbige Künstler-Wertstempelkarte mit eingedruckter 5-Pfennig-Marke Bayern, ungelaufen | H86: Nein | I86: 1911 | J86: Unbekannt | K86: Unbekannt | L86: 8 | M86: 18 | N86: =MAX(L86,M86) -> 18 | O86: Im Bestand | P86: Prinz Regent Luitpold, Bayern, 1911, 90. Geburtstag, Mädchen, Wilhelm von Diez, Oscar Consée, ungelaufen
A87: AK-2026-0086 | B87: München – Blick auf Frauenkirche und Rathaus | C87: Unbekannter Verlag (Nr. 82512) | D87: München | E87: Topografie / Ansichtskarte | F87: Gut (Z2) | G87: Farbige Litho-Ansichtskarte mit Stempel vom 30.12.1918, gelaufen | H87: Ja | I87: 1918 | J87: München / Hirschaid, 30.12.1918 | K87: Herrn Heinrich Harrer, Leyherhaus Verwalter, Hirschaid, Oberfranken | L87: 4 | M87: 8 | N87: =MAX(L87,M87) -> 8 | O87: Im Bestand | P87: München, Frauenkirche, Rathaus, 1918, Hirschaid, Oberfranken, Neujahrsgruß
A88: AK-2026-0087 | B88: Lupburg i. d. Obpf. – Ortsansicht mit Burg | C88: Kunst- und Verlagsanstalt Karl Richter, München (Nr. 49143) | D88: Lupburg (Oberpfalz) | E88: Topografie / Ansichtskarte | F88: Gut (Z2) | G88: S/W-Ansichtskarte mit Stempel Parsberg vom 31.08.1939, gelaufen, unzustellbar/zurück | H88: Ja | I88: 1939 | J88: Parsberg, 31.08.1939 | K88: Herrn Albert Guidl, Jagdfliegerschule Schülerkompanie (später korrigiert/unbekannt) | L88: 4 | M88: 10 | N88: =MAX(L88,M88) -> 10 | O88: Im Bestand | P88: Lupburg, Oberpfalz, Burg Lupburg, Karl Richter München, 1939, Parsberg, Jagdfliegerschule
A89: AK-2026-0088 | B89: Schloß Neuschwanstein, 1008 m ü. M. | C89: Gebr. Metz, Tübingen (Nr. 170 B 37) | D89: Schwangau / Füssen | E89: Topografie / Ansichtskarte | F89: Gut (Z2) | G89: S/W-Ansichtskarte mit Stempel Hohenschwangau vom 02.10.1918, gelaufen | H89: Ja | I89: 1918 | J89: Hohenschwangau / Mannheim, 02.10.1918 | K89: Familie Willi Paulen, Mannheim, Erlenstr. 50 | L89: 4 | M89: 8 | N89: =MAX(L89,M89) -> 8 | O89: Im Bestand | P89: Schloss Neuschwanstein, Schwangau, Alpen, Gebr. Metz Tübingen, 1918, Mannheim
A90: AK-2026-0089 | B90: Marktredwitz – Am Schwanenteich im Stadtpark | C90: Otto Oertel, Marktredwitz (Verlag VI 1921) | D90: Marktredwitz | E90: Topografie / Ansichtskarte | F90: Sehr gut (Z1-) | G90: Farbige Litho-Ansichtskarte mit historischer Notiz, ungelaufen | H90: Nein | I90: Um 1921 | J90: Unbekannt | K90: Unbekannt | L90: 5 | M90: 10 | N90: =MAX(L90,M90) -> 10 | O90: Im Bestand | P90: Marktredwitz, Schwanenteich, Stadtpark, Otto Oertel, Oberfranken, ungelaufen
A91: AK-2026-0090 | B91: Bad Kissingen – Kurhaus | C91: Unbekannter Verlag (Nr. 97688) | D91: Bad Kissingen | E91: Topografie / Ansichtskarte | F91: Gut (Z2) | G91: S/W-Ansichtskarte mit Stempel Bad Kissingen von 1918, gelaufen | H91: Ja | I91: 1918 | J91: Bad Kissingen / Hersbruck, 1918 | K91: Frau Anna Geriq, Hersbruck, Kirchgasse 298 | L91: 4 | M91: 8 | N91: =MAX(L91,M91) -> 8 | O91: Im Bestand | P91: Bad Kissingen, Kurhaus, Unterfranken, 1918, Hersbruck, Ansichtskarte
A92: AK-2026-0091 | B92: Pfarrkirche Parsberg (Architekt H. Hauberrisser jun., Regensburg) | C92: Meisenbach Riffarth & Co., Berlin-Schöneberg | D92: Parsberg (Oberpfalz) | E92: Topografie / Architektur / Kirche | F92: Sehr gut (Z1-) | G92: Farbiger Dreifarben-Lichtdruck, ungelaufen | H92: Nein | I92: Um 1910/1920 | J92: Unbekannt | K92: Unbekannt | L92: 5 | M92: 10 | N92: =MAX(L92,M92) -> 10 | O92: Im Bestand | P92: Parsberg, Pfarrkirche, St. Andreas, Architekt Hauberrisser, Oberpfalz, Meisenbach Riffarth, ungelaufen
A93: AK-2026-0092 | B93: Gruss aus Maria Eck (Kloster und Kirche) | C93: Franz Schemm, Kunstanstalt, Nürnberg (Nr. 3308) | D93: Maria Eck / Siegsdorf (Oberbayern) | E93: Topografie / Wallfahrtsort / Litho | F93: Gut bis Sehr gut (Z2/Z1-) | G93: Farbige Litho-Ansichtskarte mit Sonderstempel und Poststempel Siegsdorf vom 31.07.1902, gelaufen | H93: Ja | I93: 1902 | J93: Siegsdorf / Reichenhall, 31.07.1902 | K93: H. Hochwürden Herrn Pfarrer Anton Windhagen, in Bischofswiesen b. Berchtesgaden | L93: 6 | M93: 12 | N93: =MAX(L93,M93) -> 12 | O93: Im Bestand | P93: Maria Eck, Wallfahrtsort, Kloster, Siegsdorf, Oberbayern, 1902, Franz Schemm Nürnberg, Pfarrer Windhagen, Bischofswiesen
A94: AK-2026-0093 | B94: Gruß aus Regensburg (Dominikanerkirche, St. Blasius, Albertuskapelle) | C94: Alfred Coppenrath's Sortimentsbuchhandlung, Regensburg | D94: Regensburg | E94: Topografie / Mehrfachansicht / Kirche | F94: Gut bis Sehr gut (Z2/Z1-) | G94: S/W-Mehrfachansichtskarte mit Stempel Straubing vom 17.11.1917, gelaufen, mit Ankunftsstempel Wiesenfelden | H94: Ja | I94: 1917 | J94: Straubing / Wiesenfelden, 17.11.1917 | K94: Hochwürdigen Herrn Pfarrer Anton Windhagen, Wiesenfelden | L94: 6 | M94: 12 | N94: =MAX(L94,M94) -> 12 | O94: Im Bestand | P94: Regensburg, Dominikanerkirche, St. Blasius, Albertus Magnus, Alfred Coppenrath, 1917, Pfarrer Windhagen, Wiesenfelden
A95: AK-2026-0094 | B95: München – Hotel „Drei Raben“ | C95: Franz Hayer, München | D95: München | E95: Topografie / Hotel / Litho | F95: Gut bis Sehr gut (Z2/Z1-) | G95: Farbige Litho-Ansichtskarte mit Stempel München vom 24.07.1903, gelaufen, mit Ankunftsstempel Wiesenfelden | H95: Ja | I95: 1903 | J95: München / Wiesenfelden, 24./25.07.1903 | K95: Frau Elisabeth Windhager, Privatinhaberin, Wiesenfelden b. Bogen | L95: 5 | M95: 10 | N95: =MAX(L95,M95) -> 10 | O95: Im Bestand | P95: München, Hotel Drei Raben, Franz Hayer, 1903, Wiesenfelden, Elisabeth Windhager
A96: AK-2026-0095 | B96: Gruss aus Regensburg (Kgl. Lyceum u. Studienkirche) | C96: C. Palestrini, Regensburg | D96: Regensburg | E96: Topografie / Ansichtskarte / Grafik | F96: Gut bis Sehr gut (Z2/Z1-) | G96: Historische Grafik-Ansichtskarte mit Poststempel Regensburg vom 10.01.1913, gelaufen | H96: Ja | I96: 1913 | J96: Regensburg, 10.01.1913 | K96: Familie Joseph Lauerer, Gend.-Oberkommissär, Parsberg (Opf.) | L96: 5 | M96: 10 | N96: =MAX(L96,M96) -> 10 | O96: Im Bestand | P96: Regensburg, Kgl. Lyceum, Studienkirche, C. Palestrini, 1913, Familie Lauerer, Parsberg
A97: AK-2026-0096 | B97: Schloss Parsberg (Bayerische Oberpfalz) – Prof. Hans Rud. Schulze Nr. 6 | C97: Dr. Trenkler Co., Dresden (nach Prof. Hans Rud. Schulze) | D97: Parsberg (Oberpfalz) | E97: Topografie / Schloss / Künstlerkarte | F97: Gut bis Sehr gut (Z2/Z1-) | G97: Farbige Künstler-Ansichtskarte mit Stempel Regensburg vom 10.01.1913, gelaufen | H97: Ja | I97: 1913 | J97: Regensburg, 10.01.1913 | K97: Familie Joseph Lauerer, Gend.-Oberkommissär, Parsberg (Opf.) | L97: 5 | M97: 10 | N97: =MAX(L97,M97) -> 10 | O97: Im Bestand | P97: Schloss Parsberg, Oberpfalz, Prof. Hans Rud. Schulze, Deutsche Burgen, 1913, Familie Lauerer
A98: AK-2026-0097 | B98: Regensburg – Dom, Westfront und Kgl. Villa | C98: Meissner & Buch, Leipzig (Nr. 4629) | D98: Regensburg | E98: Topografie / Mehrfachansicht / Litho | F98: Gut bis Sehr gut (Z2/Z1-) | G98: Farbige Litho-Ansichtskarte mit Poststempel Regensburg, gelaufen, mit Ankunftsstempel Wiesenfelden | H98: Ja | I98: Unbekannt (ca. 1900-1910) | J98: Regensburg / Wiesenfelden | K98: Hochwürdigsten Hochgeschätzten Herrn Anton Windhager, Pfarrer, Wiesenfelden (Niederbayern) | L98: 5 | M98: 10 | N98: =MAX(L98,M98) -> 10 | O98: Im Bestand | P98: Regensburg, Dom Westfront, Königliche Villa, Meissner & Buch, Pfarrer Anton Windhager, Wiesenfelden
A99: AK-2026-0098 | B99: Schloss Parsberg (Bayerische Oberpfalz) – Prof. Hans Rud. Schulze Nr. 6 | C99: Dr. Trenkler Co., Dresden (nach Prof. Hans Rud. Schulze) | D99: Parsberg (Oberpfalz) | E99: Topografie / Schloss / Künstlerkarte | F99: Sehr gut (Z1-) | G99: Farbige Künstler-Ansichtskarte, ungelaufen, unbeschrieben | H99: Nein | I99: Um 1910/1915 | J99: Unbekannt | K99: Unbekannt | L99: 4 | M99: 10 | N99: =MAX(L99,M99) -> 10 | O99: Im Bestand | P99: Schloss Parsberg, Oberpfalz, Prof. Hans Rud. Schulze, Deutsche Burgen, ungelaufen
A100: AK-2026-0099 | B100: Gruss aus Schladming (Steiermark) – Mehrfachansicht mit Seilbahn & Natur | C100: P. Ledermann, Wien I. | D100: Schladming (Steiermark, Österreich) | E100: Topografie / Mehrfachansicht / Echtfotokarte | F100: Sehr gut (Z1-) | G100: Schwarz-weiße Echtfotokarte mit Poststempel Radstadt vom 21.08.1959, gelaufen | H100: Ja | I100: 1959 | J100: Radstadt, 21.08.1959 | K100: Frau Elsbeth Weiß, (13a) Wareldorf b. Mgg. / Am Weihersee (Deutschland) | L100: 4 | M100: 8 | N100: =MAX(L100,M100) -> 8 | O100: Im Bestand | P100: Schladming, Steiermark, Echtfoto, Mehrfachansicht, Seilbahn, Radstadt, 1959, Familie Weiß
A101: AK-2026-0100 | B101: Gruss aus dem Klerikal-Seminar (Regensburg) | C101: Joh. Graf, Regensburg | D101: Regensburg | E101: Topografie / Sakralbau / Litho | F101: Gut bis Sehr gut (Z2/Z1-) | G101: Lithografische Ansichtskarte, auf Vorderseite beschrieben und gelaufen, mit Stempel vom 12./13.06.1902 | H101: Ja | I101: 1902 | J101: Regensburg, 12.06.1902 (Ankunft Wiesenfelden 13.06.1902) | K101: Hh. Pfarrer Anton Windhager, Wiesenfelden, Bayr. Wald | L101: 5 | M101: 10 | N101: =MAX(L101,M101) -> 10 | O101: Im Bestand | P101: Regensburg, Klerikarseminar, St. Wolfgang, Joh. Graf, Pfarrer Anton Windhager, Wiesenfelden, 1902
A102: AK-2026-0101 | B102: Rothenburg ob der Tauber – Burgtor | C102: Gerhard Blümlein & Co., Frankfurt a. M. (Nr. 20/7) | D102: Rothenburg ob der Tauber | E102: Topografie / Stadtansicht / Tor | F102: Sehr gut (Z1-) | G102: Historische Ansichtskarte, postalisch gelaufen mit Stempel vom 12.03.1914 | H102: Ja | I102: 1914 | J102: Rothenburg o. T., 12.03.1914 | K102: Herrn Seminarist Georg Schrems, Schwabach, Seminar | L102: 4 | M102: 8 | N102: =MAX(L102,M102) -> 8 | O102: Im Bestand | P102: Rothenburg ob der Tauber, Burgtor, Blümlein, Seminarist Georg Schrems, Schwabach, 1914
A103: AK-2026-0102 | B103: Gruss aus dem Maintal (Vierzehnheiligen – Staffelberg – Schloss Banz) | C103: Kunstverlag J. Hospe, Staffelstein (Nr. 11/68) | D103: Maintal / Staffelstein / Vierzehnheiligen | E103: Topografie / Landschaft / Kunstkarte | F103: Sehr gut (Z1-) | G103: Schwarz-weiße Ansichtskarte (Echte Photographie nach Zeichnung), ungelaufen, unbeschrieben | H103: Nein | I103: Um 1920/1930 | J103: Unbekannt | K103: Unbekannt | L103: 4 | M103: 8 | N103: =MAX(L103,M103) -> 8 | O103: Im Bestand | P103: Maintal, Vierzehnheiligen, Staffelberg, Schloss Banz, Hospe Staffelstein, ungelaufen
A104: AK-2026-0103 | B104: Kloster Weltenburg an der Donau | C104: Martin Herpich, Kunst- u. Verlagsanstalt, München (Nr. 865) | D104: Kelheim / Weltenburg (Niederbayern) | E104: Topografie / Kloster / Donau / Uvachrom | F104: Sehr gut (Z1-) | G104: Farbige Ansichtskarte nach Uvachrom-Aufnahme, mit Poststempel Kelheim vom 13.06.1944, gelaufen | H104: Ja | I104: 1944 | J104: Kelheim, 13.06.1944 | K104: Fam. Joseph Sauerer, Gend. Oberk., Lupburg 10pf. bei Parsberg | L104: 4 | M104: 8 | N104: =MAX(L104,M104) -> 8 | O104: Im Bestand | P104: Kloster Weltenburg, Donau, Kelheim, Herpich München, Uvachrom, Familie Sauerer, Lupburg, 1944
A105: AK-2026-0104 | B105: Neigermühle b. Regen / Bayer. Wald – Seegasthof und Mühle | C105: Schöning & Co., Lübeck (Bestellnr. Regen 69) | D105: Neigermühle / Regen (Bayerischer Wald) | E105: Topografie / Gasthof / Natur | F105: Sehr gut (Z1-) | G105: Schwarz-weiße Ansichtskarte (Foto), mit Poststempel Regen vom 06.06.1957, gelaufen | H105: Ja | I105: 1957 | J105: Regen, 06.06.1957 | K105: Fam. Josef Sauerer, Lupburg, Opf. bei Parsberg | L105: 4 | M105: 8 | N105: =MAX(L105,M105) -> 8 | O105: Im Bestand | P105: Neigermühle, Regen, Bayerischer Wald, Seegasthof Klimmer, Schöning Lübeck, Familie Sauerer, Lupburg, 1957
A106: AK-2026-0105 | B106: Gruss aus Lupburg (Oberpfalz) – Gesamtansicht mit Burg | C106: Joh. Landfried, Lupburg | D106: Lupburg (Oberpfalz) | E106: Topografie / Ortsansicht / Burg | F106: Gut bis Sehr gut (Z2/Z1-) | G106: Historische Ansichtskarte (Soldatenkarte, gebührenfrei), gelaufen mit Poststempel vom 16.09.1908 | H106: Ja | I106: 1908 | J106: Lupburg, 16.09.1908 | K106: Herrn Josef Sauerer, Wohlgeboren, Grünstande, Post Hemau | L106: 5 | M106: 13 | N106: =MAX(L106,M106) -> 13 | O106: Im Bestand | P106: Lupburg, Oberpfalz, Burg Lupburg, Landfried, Soldatenkarte, Josef Sauerer, Grünstande, Hemau, 1908
A107: AK-2026-0106 | B107: Neue kath. Pfarrkirche Seubersdorf / Opf. | C107: Bildkunst-Verlag Poppe, Bad Kissingen (Nr. 1646) | D107: Seubersdorf in der Oberpfalz | E107: Topografie / Sakralbau / Kirche | F107: Sehr gut (Z1-) | G107: Schwarz-weiße Echtfotokarte mit eingedrucktem Weihe-Gedenken (1949), handschriftlich datiert 12.04.1953 | H107: Nein | I107: 1953 | J107: Seubersdorf, 12.04.1953 | K107: Familie Sauerer-Bartman | L107: 4 | M107: 13 | N107: =MAX(L107,M107) -> 13 | O107: Im Bestand | P107: Seubersdorf, Oberpfalz, Pfarrkirche, Poppe Bad Kissingen, Konsekration 1949, Heilige Mission 1953, Familie Sauerer-Bartman
...

Sheet Save
